{
  "lastUpdated": "2026-04-04T07:51:32.640Z",
  "count": 10,
  "articles": [
    {
      "title": "İsrail ordusu, Tahran genelinde altyapı tesislerini hedef aldı",
      "description": "İsrail ordusu, ABD ile ortak saldırıları sürdürdükleri İran'ın başkenti Tahran genelinde altyapı tesislerine hava saldırıları gerçekleştirildiğini duyurdu.",
      "url": "https://www.aa.com.tr/tr/guncel/israil-ordusu-tahran-genelinde-altyapi-tesislerini-hedef-aldi/3891373",
      "image": "",
      "date": "2026-04-04T07:43:07.000Z",
      "source": "Anadolu Ajansı",
      "lang": "tr",
      "category": "almanya",
      "type": "rss"
    },
    {
      "title": "Sultanlar Ligi'nde play-off final ve 3-4 etapları programı güncellendi",
      "description": "Voleybol Vodafone Sultanlar Ligi play-off final ve 3-4 etapları maç programında değişiklik yapıldı.",
      "url": "https://www.aa.com.tr/tr/guncel/sultanlar-liginde-play-off-final-ve-3-4-etaplari-programi-guncellendi/3891367",
      "image": "",
      "date": "2026-04-04T07:35:04.000Z",
      "source": "Anadolu Ajansı",
      "lang": "tr",
      "category": "almanya",
      "type": "rss"
    },
    {
      "title": "Futbolcu İsmail Yüksek hakkında bahis soruşturmasında takipsizlik kararı verildi",
      "description": "\"Futbolda bahis\" iddiasına ilişkin yürütülen soruşturmada, futbolcu İsmail Yüksek hakkında takipsizlik kararı verildi.",
      "url": "https://www.aa.com.tr/tr/guncel/futbolcu-ismail-yuksek-hakkinda-bahis-sorusturmasinda-takipsizlik-karari-verildi/3891357",
      "image": "",
      "date": "2026-04-04T07:25:09.000Z",
      "source": "Anadolu Ajansı",
      "lang": "tr",
      "category": "almanya",
      "type": "rss"
    },
    {
      "title": "Çanakkale ve Edirne'de sağanak hayatı olumsuz etkiledi",
      "description": "Çanakkale ve Edirne'de aralıklarla devam eden sağanak yaşamı olumsuz etkiledi.",
      "url": "https://www.aa.com.tr/tr/guncel/canakkale-ve-edirnede-saganak-hayati-olumsuz-etkiledi/3891356",
      "image": "",
      "date": "2026-04-04T07:23:39.000Z",
      "source": "Anadolu Ajansı",
      "lang": "tr",
      "category": "almanya",
      "type": "rss"
    },
    {
      "title": "Kars ve Ardahan'da ilkbaharda kar etkili oldu",
      "description": "Kars'ın Sarıkamış ilçesinde gece başlayan ve aralıklarla devam eden kar, sarıçam ormanları, bitkiler ve araçların üzerini beyaza bürüdü.",
      "url": "https://www.aa.com.tr/tr/guncel/kars-ve-ardahanda-ilkbaharda-kar-etkili-oldu/3891355",
      "image": "",
      "date": "2026-04-04T07:23:27.000Z",
      "source": "Anadolu Ajansı",
      "lang": "tr",
      "category": "almanya",
      "type": "rss"
    },
    {
      "title": "Mehrfamilienhaus in Berlin-Neukölln nach Brand unbewohnbar",
      "description": "",
      "url": "https://www.rbb24.de/panorama/beitrag/2026/04/berlin-neukoelln-brand-haus-unbewohnbar-feuerwehr.html",
      "image": "",
      "date": "2026-04-04T07:07:37.000Z",
      "source": "RBB24 Berlin",
      "lang": "de",
      "category": "berlin",
      "type": "rss"
    },
    {
      "title": "Brand auf Deponie in Cottbus dauert an - Warnung vor Rauch",
      "description": "",
      "url": "https://www.rbb24.de/panorama/beitrag/2026/04/cottbus-brand-deponie-gruenabfaelle-feuerwehr.html",
      "image": "",
      "date": "2026-04-04T07:02:11.000Z",
      "source": "RBB24 Berlin",
      "lang": "de",
      "category": "berlin",
      "type": "rss"
    },
    {
      "title": "\"La Belle\"-Attentat: Überlebender Heino Möhring erinnert sich",
      "description": "Gegen 1:45 Uhr explodiert am 5. April 1986 eine Bombe in der Diskothek \"La Belle\" in Berlin-Friedenau. Bei dem Anschlag sterben drei Menschen, mehr als 200 werden teils schwer verletzt, unter ihnen Heino Möhring - der heute noch an den Spätfolgen leidet.",
      "url": "https://www.rbb24.de/panorama/beitrag/2026/04/40-jahre-attentat-la-belle-bombe-diskothek-opfer-zeitzeuge-westberlin.html",
      "image": "",
      "date": "2026-04-04T06:22:20.000Z",
      "source": "RBB24 Berlin",
      "lang": "de",
      "category": "berlin",
      "type": "rss"
    },
    {
      "title": "Volleyball-Bundesliga: BR Volleys erreichen Halbfinale",
      "description": "Die BR Volleys haben im Playoff-Viertelfinale der Volleyball-Bundesliga die Netzhoppers KW besiegt. Die Berliner gewannen auch das zweite Spiel und entschieden die Best-of-three-Serie so vorzeitig für sich.",
      "url": "https://www.rbb24.de/sport/beitrag/2026/04/volleyball-berlin-brandenburg-br-volleys-netzhoppers-bundesliga-viertelfinale.html",
      "image": "",
      "date": "2026-04-03T19:42:24.000Z",
      "source": "RBB24 Berlin",
      "lang": "de",
      "category": "berlin",
      "type": "rss"
    },
    {
      "title": "Berlin: Rolltreppen-Chaos am Hauptbahnhof behoben",
      "description": "Seit Mitte Februar waren zahlreiche Rolltreppen am Berliner Hauptbahnhof außer Betrieb. Nun läuft der Verkehr laut Bahn wieder weitgehend normal – eine spürbare Entlastung nach Wochen voller Kofferschleppen.",
      "url": "https://www.rbb24.de/panorama/beitrag/2026/04/berlin-rolltreppen-hauptbahnhof-defekt-behoben.html",
      "image": "",
      "date": "2026-04-03T15:41:08.000Z",
      "source": "RBB24 Berlin",
      "lang": "de",
      "category": "berlin",
      "type": "rss"
    }
  ],
  "insights": {
    "weatherAdvice": "Berlin'de güzel bir gün dileriz!",
    "newsBrief": "Berlin gündemi her zaman hareketli."
  }
}