{
  "lastUpdated": "2026-03-27T21:52:46.961Z",
  "count": 10,
  "articles": [
    {
      "title": "İletişim Başkanı Duran, STRATCOM Zirvesi'nde görüşmeler gerçekleştirdi",
      "description": "Cumhurbaşkanlığı İletişim Başkanı Burhanettin Duran, Uluslararası Stratejik İletişim Zirvesi (STRATCOM Zirvesi) 2026 kapsamında görüşmeler gerçekleştirdi.",
      "url": "https://www.aa.com.tr/tr/guncel/iletisim-baskani-duran-stratcom-zirvesinde-gorusmeler-gerceklestirdi/3882428",
      "image": "",
      "date": "2026-03-27T21:31:37.000Z",
      "source": "Anadolu Ajansı",
      "lang": "tr",
      "category": "almanya",
      "type": "rss"
    },
    {
      "title": "ABD Başkanı Trump, İran'la görüşmelerin sürdüğünü belirtti",
      "description": "ABD Başkanı Donald Trump, İran'la müzakerelerin devam ettiğini belirterek, \"Onlar bizimle anlaşma yapmak istiyor.\" dedi.",
      "url": "https://www.aa.com.tr/tr/guncel/abd-baskani-trump-iranla-gorusmelerin-surdugunu-belirtti/3882412",
      "image": "",
      "date": "2026-03-27T21:06:32.000Z",
      "source": "Anadolu Ajansı",
      "lang": "tr",
      "category": "almanya",
      "type": "rss"
    },
    {
      "title": "TFF Tahkim Kurulu, Galatasaray'a verilen para cezasını onadı",
      "description": "Türkiye Futbol Federasyonu (TFF) Tahkim Kurulu, Profesyonel Futbol Disiplin Kurulu (PFDK) tarafından Galatasaray'a verilen 1 milyon 412 bin liralık para cezasını onadı.",
      "url": "https://www.aa.com.tr/tr/guncel/tff-tahkim-kurulu-galatasaraya-verilen-para-cezasini-onadi/3882369",
      "image": "",
      "date": "2026-03-27T20:33:24.000Z",
      "source": "Anadolu Ajansı",
      "lang": "tr",
      "category": "almanya",
      "type": "rss"
    },
    {
      "title": "Emircan Haney dünyada yılın en iyi okçusu seçildi",
      "description": "2025 Dünya Okçuluk Ödülleri'nin adayları arasındaki Emircan Haney, yılın okçusu seçildi.",
      "url": "https://www.aa.com.tr/tr/guncel/emircan-haney-dunyada-yilin-en-iyi-okcusu-secildi/3882367",
      "image": "",
      "date": "2026-03-27T20:31:58.000Z",
      "source": "Anadolu Ajansı",
      "lang": "tr",
      "category": "almanya",
      "type": "rss"
    },
    {
      "title": "STRATCOM Zirvesi 2026'da \"İklim Diplomasisinde Yeni Öncelikler\" paneli yapıldı",
      "description": "\"Uluslararası Stratejik İletişim Zirvesi (STRATCOM) 2026\" kapsamında \"İklim Diplomasisinde Yeni Öncelikler\" paneli düzenlendi.",
      "url": "https://www.aa.com.tr/tr/guncel/stratcom-zirvesi-2026da-iklim-diplomasisinde-yeni-oncelikler-paneli-yapildi/3882366",
      "image": "",
      "date": "2026-03-27T20:30:55.000Z",
      "source": "Anadolu Ajansı",
      "lang": "tr",
      "category": "almanya",
      "type": "rss"
    },
    {
      "title": "Regionalliga: Babelsberg mit Schützenfest gegen Chemie Leipzig",
      "description": "",
      "url": "https://www.rbb24.de/sport/beitrag/2026/03/fussball-regionalliga-nordost-babelsberg-chemie-leipzig.html",
      "image": "",
      "date": "2026-03-27T20:23:22.000Z",
      "source": "RBB24 Berlin",
      "lang": "de",
      "category": "berlin",
      "type": "rss"
    },
    {
      "title": "A100 in Richtung Treptow auf einer Spur befahrbar - Sperrung nach Brand aufgehoben",
      "description": "",
      "url": "https://www.rbb24.de/panorama/beitrag/2026/03/a100-stau-sperrung.html",
      "image": "",
      "date": "2026-03-27T19:13:52.000Z",
      "source": "RBB24 Berlin",
      "lang": "de",
      "category": "berlin",
      "type": "rss"
    },
    {
      "title": "Neues Stadtquartier in Berlin-Pankow: Siegerentwurf für Elisabeth-Aue gekürt",
      "description": "",
      "url": "https://www.rbb24.de/wirtschaft/beitrag/2026/03/neues-stadtquartier-elisabeth-aue-siegerentwurf-gekuert.html",
      "image": "",
      "date": "2026-03-27T18:42:06.000Z",
      "source": "RBB24 Berlin",
      "lang": "de",
      "category": "berlin",
      "type": "rss"
    },
    {
      "title": "Wölfe stehen jetzt als jagdbare Art im Gesetz",
      "description": "",
      "url": "https://www.rbb24.de/panorama/beitrag/2026/03/woelfe-abschuss-jagdgesetz-bund-bundesrat-beschluss.html",
      "image": "",
      "date": "2026-03-27T18:33:29.000Z",
      "source": "RBB24 Berlin",
      "lang": "de",
      "category": "berlin",
      "type": "rss"
    },
    {
      "title": "Alba-Arena in Adlershof: Basketballer planen großen Campus",
      "description": "Dass Alba Berlin eine neue Arena in Adlershof bauen will, wurde kürzlich schon bekannt. Am Freitag wurden die Pläne im Abgeordnetenhaus präsentiert - danach soll die Halle sogar bis zu 20.000 Plätze bekommen. Zudem soll ein ganzer Campus auf dem Gelände entstehen.",
      "url": "https://www.rbb24.de/sport/beitrag/2026/03/basketball-bbl-nba-europe-uber-arena-alba-berlin-sportausschuss-baldi-adlershof.html",
      "image": "",
      "date": "2026-03-27T17:30:19.000Z",
      "source": "RBB24 Berlin",
      "lang": "de",
      "category": "berlin",
      "type": "rss"
    }
  ],
  "insights": {
    "weatherAdvice": "Berlin'de güzel bir gün dileriz!",
    "newsBrief": "Berlin gündemi her zaman hareketli."
  }
}