{
  "lastUpdated": "2026-05-15T14:05:20.294Z",
  "count": 10,
  "articles": [
    {
      "title": "Kırşehir'de 5. AR-GE Proje Pazarı ve 3. Cacabey Bilim Şenliği başladı",
      "description": "Kırşehir Ahi Evran Üniversitesinin (KAEÜ) ev sahipliğinde, 5. AR-GE Proje Pazarı ve Tanıtım Günleri ile 3. Cacabey Bilim Şenliği başladı.",
      "url": "https://www.aa.com.tr/tr/bilim-teknoloji/kirsehirde-5-ar-ge-proje-pazari-ve-3-cacabey-bilim-senligi-basladi/3938728",
      "image": "",
      "date": "2026-05-15T13:54:40.000Z",
      "source": "Anadolu Ajansı",
      "lang": "tr",
      "category": "almanya",
      "type": "rss"
    },
    {
      "title": "Verdi ruft Mitarbeiter im Großhandel zu Warnstreik auf",
      "description": "",
      "url": "https://www.rbb24.de/wirtschaft/beitrag/2026/05/verdi-warnstreik-berlin-brandenburg-grosshandel.html",
      "image": "",
      "date": "2026-05-15T13:29:12.000Z",
      "source": "RBB24 Berlin",
      "lang": "de",
      "category": "berlin",
      "type": "rss"
    },
    {
      "title": "Eskişehir'in Tepebaşı Belediyesine yönelik operasyonda gözaltı sayısı 25'e yükseldi",
      "description": "Eskişehir merkezli operasyonda, aralarında Tepebaşı Belediyesi görevlilerinin bulunduğu gözaltına alınan şüpheli sayısı 25'e yükseldi.",
      "url": "https://www.aa.com.tr/tr/gundem/eskisehirin-tepebasi-belediyesine-yonelik-operasyonda-gozalti-sayisi-25e-yukseldi/3938715",
      "image": "",
      "date": "2026-05-15T13:28:28.000Z",
      "source": "Anadolu Ajansı",
      "lang": "tr",
      "category": "almanya",
      "type": "rss"
    },
    {
      "title": "Bakan Şimşek: Bütçe performansımız hedeflerle uyumlu seyrediyor",
      "description": "Hazine ve Maliye Bakanı Mehmet Şimşek, bütçe performansının hedeflerle uyumlu seyrettiğini belirterek, \"Faiz dışı bütçe dengesi, bütün zorlu koşullara rağmen ilk 4 ayda yıllık 536 milyar lira iyileşti.\" ifadesini kullandı.",
      "url": "https://www.aa.com.tr/tr/ekonomi/bakan-simsek-butce-performansimiz-hedeflerle-uyumlu-seyrediyor/3938698",
      "image": "",
      "date": "2026-05-15T13:19:36.000Z",
      "source": "Anadolu Ajansı",
      "lang": "tr",
      "category": "almanya",
      "type": "rss"
    },
    {
      "title": "Sınır Tanımayan Gazeteciler, İsrail'in NYT gazetesine yönelik gözdağı girişimini kınadı",
      "description": "Sınır Tanımayan Gazeteciler (RSF), İsraillilerin Filistinli esirlere yönelik işkence ve cinsel şiddet uygulamalarını ortaya koyan The New York Times (NYT) gazetesine yönelik gözdağı verme girişimini kınadığını bildirdi.",
      "url": "https://www.aa.com.tr/tr/dunya/sinir-tanimayan-gazeteciler-israilin-nyt-gazetesine-yonelik-gozdagi-girisimini-kinadi/3938687",
      "image": "",
      "date": "2026-05-15T13:17:08.000Z",
      "source": "Anadolu Ajansı",
      "lang": "tr",
      "category": "almanya",
      "type": "rss"
    },
    {
      "title": "Gratis Kunst: 100 Museen in Berlin und Brandenburg nehmen am Museumstag teil",
      "description": "",
      "url": "https://www.rbb24.de/panorama/beitrag/2026/05/100-museen-museumstag-brandenburg.html",
      "image": "",
      "date": "2026-05-15T13:05:32.000Z",
      "source": "RBB24 Berlin",
      "lang": "de",
      "category": "berlin",
      "type": "rss"
    },
    {
      "title": "İtalyan voleybolcu Giannelli'den milli oyuncu Efe Mandıracı'ya övgü",
      "description": "CEV Erkekler Şampiyonlar Ligi'nde kupanın son sahibi İtalyan kulübü Sir Sicoma Monini Perugia'nın pasörü Simone Giannelli, kariyerini İtalya liginde sürdüren milli voleybolcu Efe Mandıracı'dan övgüyle bahsetti.",
      "url": "https://www.aa.com.tr/tr/spor/italyan-voleybolcu-giannelliden-milli-oyuncu-efe-mandiraciya-ovgu/3938656",
      "image": "",
      "date": "2026-05-15T12:42:16.000Z",
      "source": "Anadolu Ajansı",
      "lang": "tr",
      "category": "almanya",
      "type": "rss"
    },
    {
      "title": "Viehdiebstahl in Brandenburg: Mehr Kontrollen von Tansporten",
      "description": "Nach mehreren Viehdiebstählen in Brandenburg hat Innenminister Redmann verstärkte Kontrollen angekündigt. Eine Ermittlungsgruppe sei eingerichtet worden - der Blick richtet sich auch ins Ausland. Die Taten erinnern an ähnliche Vorfälle vor mehr als zehn Jahren.",
      "url": "https://www.rbb24.de/panorama/beitrag/2026/05/vieh-diebstaehle-suedbrandenburg-minister-herzberg.html",
      "image": "",
      "date": "2026-05-15T11:13:26.000Z",
      "source": "RBB24 Berlin",
      "lang": "de",
      "category": "berlin",
      "type": "rss"
    },
    {
      "title": "Polen: Erste gleichgeschlechtliche Ehe in Warschau eingetragen",
      "description": "Zwei Männer aus Polen, die in Berlin geheiratet haben, konnten ihre Ehe nun auch in Warschau anerkennen lassen. Die queere Community in Polen feiert das als historischen Schritt.",
      "url": "https://www.rbb24.de/panorama/beitrag/2026/05/rathaus-warschau-polen-gleichgeschlechtliche-ehe-anerkannt.html",
      "image": "",
      "date": "2026-05-15T09:55:20.000Z",
      "source": "RBB24 Berlin",
      "lang": "de",
      "category": "berlin",
      "type": "rss"
    },
    {
      "title": "Berliner Bürgerämter erreichen erstmals 14-Tage-Ziel",
      "description": "",
      "url": "https://www.rbb24.de/panorama/beitrag/2026/05/berlins-buergeraemter-erreichen-erstmals-14-tage-ziel.html",
      "image": "",
      "date": "2026-05-15T09:03:03.000Z",
      "source": "RBB24 Berlin",
      "lang": "de",
      "category": "berlin",
      "type": "rss"
    }
  ],
  "insights": {
    "weatherAdvice": "Berlin'de güzel bir gün dileriz!",
    "newsBrief": "Berlin gündemi her zaman hareketli."
  }
}