{
  "lastUpdated": "2026-06-30T07:52:47.025Z",
  "count": 10,
  "articles": [
    {
      "title": "Bakan Göktaş: 11 bin 22 çocuğumuz koruyucu ailelerinin yanında sevgiyle büyüyor",
      "description": "Aile ve Sosyal Hizmetler Bakanı Göktaş, \"Bugün, 11 bin 22 çocuğumuz koruyucu ailelerinin yanında sevgiyle büyüyor. Bir çocuğun hayatına sevgiyle eşlik etmek isteyen vatandaşlarımızı bu gönül birlikteliğine davet ediyorum.\" ifadelerini kullandı.",
      "url": "https://www.aa.com.tr/tr/gundem/bakan-goktas-11-bin-22-cocugumuz-koruyucu-ailelerinin-yaninda-sevgiyle-buyuyor/3981922",
      "image": "",
      "date": "2026-06-30T07:44:00.000Z",
      "source": "Anadolu Ajansı",
      "lang": "tr",
      "category": "almanya",
      "type": "rss"
    },
    {
      "title": "Emine Erdoğan, Koruyucu Aile Günü'nü kutladı",
      "description": "Emine Erdoğan, koruyucu anne ve babaların Koruyucu Aile Günü'nü tebrik etti.",
      "url": "https://www.aa.com.tr/tr/gundem/emine-erdogan-koruyucu-aile-gununu-kutladi/3981906",
      "image": "",
      "date": "2026-06-30T07:28:58.000Z",
      "source": "Anadolu Ajansı",
      "lang": "tr",
      "category": "almanya",
      "type": "rss"
    },
    {
      "title": "Dış ticaret istatistikleri açıklandı",
      "description": "Türkiye'nin ihracatı, mayısta geçen yılın aynı ayına kıyasla yüzde 9,5 azalarak 22 milyar 461 milyon dolar, ithalatı yüzde 10,8 düşüşle 28 milyar 71 milyon dolar olarak gerçekleşti.",
      "url": "https://www.aa.com.tr/tr/ekonomi/dis-ticaret-istatistikleri-aciklandi/3981904",
      "image": "",
      "date": "2026-06-30T07:28:05.000Z",
      "source": "Anadolu Ajansı",
      "lang": "tr",
      "category": "almanya",
      "type": "rss"
    },
    {
      "title": "Güneşten elektrik üretiminde yılın rekoru tazelendi",
      "description": "Türkiye'de güneş enerjisinden günlük bazda üretilen elektrik, dün 193 bin 695 megavatsaatle yılın en yüksek seviyesine ulaştı.",
      "url": "https://www.aa.com.tr/tr/ekonomi/gunesten-elektrik-uretiminde-yilin-rekoru-tazelendi/3981900",
      "image": "",
      "date": "2026-06-30T07:25:48.000Z",
      "source": "Anadolu Ajansı",
      "lang": "tr",
      "category": "almanya",
      "type": "rss"
    },
    {
      "title": "Bursa'da mobilya mağazasında çıkan yangına müdahale ediliyor",
      "description": "Bursa'nın merkez Osmangazi ilçesinde bir mobilya mağazasında çıkan yangın söndürülmeye çalışılıyor.",
      "url": "https://www.aa.com.tr/tr/gundem/bursada-mobilya-magazasinda-cikan-yangina-mudahale-ediliyor/3981879",
      "image": "",
      "date": "2026-06-30T07:12:00.000Z",
      "source": "Anadolu Ajansı",
      "lang": "tr",
      "category": "almanya",
      "type": "rss"
    },
    {
      "title": "Mensch ertrinkt im Urbanhafen in Berlin-Kreuzberg",
      "description": "",
      "url": "https://www.rbb24.de/panorama/beitrag/2026/06/berlin-kreuzberg-toter-urbanhafen-ertrunken.html",
      "image": "",
      "date": "2026-06-30T06:50:26.000Z",
      "source": "RBB24 Berlin",
      "lang": "de",
      "category": "berlin",
      "type": "rss"
    },
    {
      "title": "Wetterprognose: Gewitter ziehen auf – danach wird es deutlich kühler ",
      "description": "",
      "url": "https://www.rbb24.de/panorama/beitrag/2026/06/berlin-brandenburg-gewitter-hitzewelle-regen-wetterprognose.html",
      "image": "",
      "date": "2026-06-30T06:10:50.000Z",
      "source": "RBB24 Berlin",
      "lang": "de",
      "category": "berlin",
      "type": "rss"
    },
    {
      "title": "Größter künstlicher Seenverbund Europas offiziell eröffnet",
      "description": "Fünf Seen, zwei Länder: Mit der Lausitzer Seenkette geht am Montag ein Riesenprojekt der Bergbausanierung zu Ende.",
      "url": "https://www.rbb24.de/panorama/beitrag/2026/06/lausitzer-seenland-verbund-fuenf-seen.html",
      "image": "",
      "date": "2026-06-30T06:09:28.000Z",
      "source": "RBB24 Berlin",
      "lang": "de",
      "category": "berlin",
      "type": "rss"
    },
    {
      "title": "Deutsche Nationalmannschaft: Enttäuschung in der Region nach WM-Aus",
      "description": "",
      "url": "https://www.rbb24.de/panorama/beitrag/2026/06/berlin-brandenburg-wm-ende-fans-reaktionen-deutschland.html",
      "image": "",
      "date": "2026-06-30T05:50:18.000Z",
      "source": "RBB24 Berlin",
      "lang": "de",
      "category": "berlin",
      "type": "rss"
    },
    {
      "title": "Entlassener Staatssekretär Hundt: Rücknahme der Ernennung?",
      "description": "Eigentlich haben Staatssekretäre nach ihrer Entlassung aus dem Amt Anspruch auf Übergangsgeld. Doch im Fall des Ex-Chief Digital Officers von Berlin lässt die Senatskanzlei prüfen, ob wirklich 50.000 Euro gezahlt werden müssen.",
      "url": "https://www.rbb24.de/politik/beitrag/2026/06/hundt-berlin-staatssekretaer-entlassung-uebergangsgeld.html",
      "image": "",
      "date": "2026-06-30T05:43:03.000Z",
      "source": "RBB24 Berlin",
      "lang": "de",
      "category": "berlin",
      "type": "rss"
    }
  ],
  "insights": {
    "weatherAdvice": "Berlin'de güzel bir gün dileriz!",
    "newsBrief": "Berlin gündemi her zaman hareketli."
  }
}